{"nodes": [{"id": "draft6_0_research_papers_phase1_2_llrd", "label": "Layer-wise LR Decay / LLRD (paper story)", "file_type": "paper", "source_file": "draft6.0\\research\\papers\\phase1-2\\llrd.md", "source_location": null, "source_url": null, "captured_at": null, "author": null, "contributor": null, "rationale": "ULMFiT 2018 discriminative fine-tuning: give each layer its own LR \u2014 slow what downstream reads; the precedent for the middle-layer slowdown, mirror-flipped (GD reads SCFF's TOP, so slow the LATE layers)."}, {"id": "draft6_0_research_papers_phase1_2_llrd_plasticity_gradient", "label": "Plasticity gradient (slow the read-layers)", "file_type": "rationale", "source_file": "draft6.0\\research\\papers\\phase1-2\\llrd.md", "source_location": null, "source_url": null, "captured_at": null, "author": null, "contributor": null, "rationale": "Slow the late SCFF layers GD reads, keep front layers fast/plastic; physically = weaker update coupling / bigger smoothing cap, zero extra state; the cheap cousin of BYOL's EMA-view (brake vs copy)."}], "edges": [{"source": "draft6_0_research_papers_phase1_2_llrd", "target": "draft6_0_research_papers_phase1_2_llrd_plasticity_gradient", "relation": "references", "confidence": "EXTRACTED", "confidence_score": 1.0, "source_file": "draft6.0\\research\\papers\\phase1-2\\llrd.md", "source_location": null, "weight": 1.0}, {"source": "draft6_0_research_papers_phase1_2_llrd", "target": "draft6_0_research_papers_phase1_2_byol", "relation": "references", "confidence": "EXTRACTED", "confidence_score": 1.0, "source_file": "draft6.0\\research\\papers\\phase1-2\\llrd.md", "source_location": null, "weight": 1.0}], "hyperedges": []}