{"nodes": [{"id": "draft6_0_src_phase1_exp0_figs_exp0_inv_and_rise", "label": "INV dead-units + 3-D rise-probe (exp0 default)", "file_type": "image", "source_file": "draft6.0\\src\\phase1\\exp0\\figs_exp0\\INV_and_rise.png", "source_location": null, "source_url": null, "captured_at": null, "author": null, "contributor": null, "rationale": "Two panels (median n=5). Left: dead-unit fraction vs samples-seen by layer \u2014 L1 stays 0 throughout; L2 ~0.03-0.10; L3 ~0.08-0.13; L4 highest, peaking ~0.25 near 3000 samples then easing to ~0.14 \u2014 dead units worsen with depth. Right: rise-probe on a harder 3-D 64-cluster checkerboard \u2014 SCFF per-layer linear-probe accuracy FALLS 0.59 (L1) to 0.535 (L4) while a random-projection baseline rises 0.50->0.56 and crosses SCFF near L2.5, contradicting the FF-paper hope that goodness 'rises with depth'."}], "edges": [{"source": "draft6_0_src_phase1_exp0_figs_exp0_inv_and_rise", "target": "draft6_0_src_phase1_exp0_experiment_0_doc", "relation": "references", "confidence": "INFERRED", "confidence_score": 0.85, "source_file": "draft6.0\\src\\phase1\\exp0\\figs_exp0\\INV_and_rise.png", "source_location": null, "weight": 1.0}, {"source": "draft6_0_src_phase1_exp0_figs_exp0_inv_and_rise", "target": "draft6_0_src_phase1_exp0_scff_gate", "relation": "conceptually_related_to", "confidence": "INFERRED", "confidence_score": 0.95, "source_file": "draft6.0\\src\\phase1\\exp0\\figs_exp0\\INV_and_rise.png", "source_location": null, "weight": 1.0}, {"source": "draft6_0_src_phase1_exp0_figs_exp0_inv_and_rise", "target": "draft6_0_research_survey_scff_detail_goodness", "relation": "conceptually_related_to", "confidence": "INFERRED", "confidence_score": 0.65, "source_file": "draft6.0\\src\\phase1\\exp0\\figs_exp0\\INV_and_rise.png", "source_location": null, "weight": 1.0}, {"source": "draft6_0_src_phase1_exp0_figs_exp0_inv_and_rise", "target": "draft6_0_src_phase1_exp0_figs_gate_inv_strip", "relation": "semantically_similar_to", "confidence": "INFERRED", "confidence_score": 0.75, "source_file": "draft6.0\\src\\phase1\\exp0\\figs_exp0\\INV_and_rise.png", "source_location": null, "weight": 1.0}], "hyperedges": []}